biorag/__init__.py
biorag/biorag.py
biorag/cli.py
biorag/enrichment.py
biorag/rag_embedding.py
biorag/rnaseq_analysis.py
biorag/transcriptome_embedding.py
biorag/utils.py
biorag-0.1.7.dist-info/METADATA
biorag-0.1.7.dist-info/WHEEL
biorag-0.1.7.dist-info/entry_points.txt
biorag-0.1.7.dist-info/RECORD
