Metadata-Version: 2.1
Name: biorag
Version: 0.1.7
Summary: BioRAG: A tool for textual and gene set search against ARCHS4 data
Author: wchin
Author-email: wee.chin@health.wa.gov.au
Requires-Python: >=3.9,<4.0
Classifier: Programming Language :: Python :: 3
Classifier: Programming Language :: Python :: 3.9
Classifier: Programming Language :: Python :: 3.10
Classifier: Programming Language :: Python :: 3.11
Classifier: Programming Language :: Python :: 3.12
Requires-Dist: anndata (>=0.10.6,<0.11.0)
Requires-Dist: archs4py (>=0.2.12,<0.3.0)
Requires-Dist: coverage (>=7.4.4,<8.0.0)
Requires-Dist: decoupler (>=1.6.0,<2.0.0)
Requires-Dist: pandas (==2.0.2)
Requires-Dist: pytest (>=8.1.1,<9.0.0)
Requires-Dist: pytest-codecov (>=0.5.1,<0.6.0)
Requires-Dist: pytest-cov (>=4.1.0,<5.0.0)
Requires-Dist: scipy (>=1.12.0,<2.0.0)
Requires-Dist: sentence-transformers (>=2.5.1,<3.0.0)
Requires-Dist: statsmodels (>=0.14.1,<0.15.0)
